brix/__init__.py
brix-0.1.dist-info/LICENCE
brix-0.1.dist-info/METADATA
brix-0.1.dist-info/WHEEL
brix-0.1.dist-info/top_level.txt
brix-0.1.dist-info/RECORD
