Metadata-Version: 2.1
Name: brix
Version: 0.1
Summary: Brix is a library
Home-page: https://github.com/tsanikgr/brix
Author: Nikos Tsaou
Author-email: ntsaoussis@gmail.com
License: UNKNOWN
Platform: UNKNOWN
Classifier: Programming Language :: Python :: 3
Classifier: License :: OSI Approved :: MIT License
Classifier: Operating System :: OS Independent
